ovos_phal_plugin_ipgeo/__init__.py
ovos_phal_plugin_ipgeo/version.py
ovos_phal_plugin_ipgeo-0.1.7.dist-info/licenses/LICENSE
ovos_phal_plugin_ipgeo-0.1.7.dist-info/METADATA
ovos_phal_plugin_ipgeo-0.1.7.dist-info/WHEEL
ovos_phal_plugin_ipgeo-0.1.7.dist-info/entry_points.txt
ovos_phal_plugin_ipgeo-0.1.7.dist-info/top_level.txt
ovos_phal_plugin_ipgeo-0.1.7.dist-info/zip-safe
ovos_phal_plugin_ipgeo-0.1.7.dist-info/RECORD
